README.md
setup.py
dynaconfig/DataTable.py
dynaconfig/__init__.py
dynaconfig/exceptions.py
dynaconfig/file_parsers.py
dynaconfig/filters.py
dynaconfig/read.py
dynaconfig/render.py
dynaconfig/units.py
dynaconfig/utils.py
dynaconfig.egg-info/PKG-INFO
dynaconfig.egg-info/SOURCES.txt
dynaconfig.egg-info/dependency_links.txt
dynaconfig.egg-info/entry_points.txt
dynaconfig.egg-info/requires.txt
dynaconfig.egg-info/top_level.txt
dynaconfig/scripts/__init__.py
dynaconfig/scripts/cli.py